Tool.py
sztestlib/__init__.py
sztestlib/szlibone.py
shenjingbing-1.0.0.dist-info/LICENSE.txt
shenjingbing-1.0.0.dist-info/METADATA
shenjingbing-1.0.0.dist-info/WHEEL
shenjingbing-1.0.0.dist-info/top_level.txt
shenjingbing-1.0.0.dist-info/RECORD
