Metadata-Version: 2.1
Name: shenjingbing
Version: 1.0.0
Summary: this is a lihailihai lib
Home-page: UNKNOWN
Author: dameinu
Author-email: 2796185835@qq.com
License: MIT
Platform: UNKNOWN
